cliframe.py
cliframe-0.1.1.dist-info/METADATA
cliframe-0.1.1.dist-info/WHEEL
cliframe-0.1.1.dist-info/entry_points.txt
cliframe-0.1.1.dist-info/RECORD
