Metadata-Version: 2.3
Name: cliframe
Version: 0.1.1
Summary: A CLI Frame-work
Author: Artur Zdolinski
Author-email: artur@zdolinski.com
Requires-Python: >=3.10
Classifier: Programming Language :: Python :: 3
Classifier: Programming Language :: Python :: 3.10
Classifier: Programming Language :: Python :: 3.11
Classifier: Programming Language :: Python :: 3.12
Classifier: Programming Language :: Python :: 3.13
Provides-Extra: dev
Requires-Dist: pytest (>=8.4.1,<9.0.0) ; extra == "dev"
